mapistar/__init__.py
mapistar/actes/__init__.py
mapistar/actes/actesviews.py
mapistar/actes/models.py
mapistar/actes/permissions.py
mapistar/actes/urls.py
mapistar/actes/views.py
mapistar/actes/migrations/0001_initial.py
mapistar/actes/migrations/0002_auto_20180228_1517.py
mapistar/actes/migrations/0003_prescriptionlibre.py
mapistar/actes/migrations/__init__.py
mapistar/actes/schemas/__init__.py
mapistar/actes/schemas/base.py
mapistar/actes/schemas/observation.py
mapistar/actes/schemas/presciptionlibre.py
mapistar/patients/__init__.py
mapistar/patients/models.py
mapistar/patients/schemas.py
mapistar/patients/urls.py
mapistar/patients/views.py
mapistar/patients/migrations/0001_initial.py
mapistar/patients/migrations/0002_patient_birthdate.py
mapistar/patients/migrations/__init__.py
mapistar/users/__init__.py
mapistar/users/authentication.py
mapistar/users/models.py
mapistar/users/schemas.py
mapistar/users/urls.py
mapistar/users/utils.py
mapistar/users/views.py
mapistar/users/migrations/0001_initial.py
mapistar/users/migrations/__init__.py
mapistar/utils/__init__.py
mapistar/utils/schemas.py
mapistar/utils/shortcuts.py
mapistar-0.1.0.dist-info/DESCRIPTION.rst
mapistar-0.1.0.dist-info/METADATA
mapistar-0.1.0.dist-info/RECORD
mapistar-0.1.0.dist-info/WHEEL
mapistar-0.1.0.dist-info/dependency_links.txt
mapistar-0.1.0.dist-info/metadata.json
mapistar-0.1.0.dist-info/pbr.json
mapistar-0.1.0.dist-info/top_level.txt
