Metadata-Version: 2.0
Name: mapistar
Version: 0.1.0
Summary: Api pour ma gestion d'un dossier médical sous Apistar
Home-page: https://github.com/jgirardet/mapistar
Author: Jimmy Girardet
Author-email: ijkl@netc.fr
License: UNKNOWN
Platform: UNKNOWN
Requires-Dist: apistar
Requires-Dist: apistar-shell (==1.0)
Requires-Dist: attrs (==17.4.0)
Requires-Dist: certifi (==2018.1.18)
Requires-Dist: chardet (==3.0.4)
Requires-Dist: coreapi (==2.3.3)
Requires-Dist: coreschema (==0.0.4)
Requires-Dist: decorator (==4.2.1)
Requires-Dist: django (==2.0.2)
Requires-Dist: idna (==2.6)
Requires-Dist: ipython-genutils (==0.2.0)
Requires-Dist: ipython (==6.2.1)
Requires-Dist: itypes (==1.1.0)
Requires-Dist: jedi (==0.11.1)
Requires-Dist: jinja2 (==2.10)
Requires-Dist: markupsafe (==1.0)
Requires-Dist: parso (==0.1.1)
Requires-Dist: pbr (==3.1.1)
Requires-Dist: pexpect (==4.3.1)
Requires-Dist: pickleshare (==0.7.4)
Requires-Dist: pluggy (==0.6.0)
Requires-Dist: prompt-toolkit (==1.0.15)
Requires-Dist: psycopg2 (==2.7.3.2)
Requires-Dist: ptyprocess (==0.5.2)
Requires-Dist: py (==1.5.2)
Requires-Dist: pygments (==2.2.0)
Requires-Dist: pytest (==3.4.0)
Requires-Dist: pytz (==2017.3)
Requires-Dist: requests (==2.18.4)
Requires-Dist: simplegeneric (==0.8.1)
Requires-Dist: six (==1.11.0)
Requires-Dist: traitlets (==4.3.2)
Requires-Dist: uritemplate (==3.0.0)
Requires-Dist: urllib3 (==1.22)
Requires-Dist: wcwidth (==0.1.7)
Requires-Dist: werkzeug (==0.14.1)
Requires-Dist: whitenoise (==3.3.1)
